apexomni/__init__.py
apexomni/_websocket_stream.py
apexomni/constants.py
apexomni/errors.py
apexomni/eth.py
apexomni/exceptions.py
apexomni/http_private.py
apexomni/http_private_sign.py
apexomni/http_private_stark_key_sign.py
apexomni/http_private_v3.py
apexomni/http_public.py
apexomni/models.py
apexomni/websocket_api.py
apexomni/abi/erc20.json
apexomni/abi/starkware-perpetuals.json
apexomni/arm/__init__.py
apexomni/arm/libzklink_sdk.dylib
apexomni/arm/zklink_sdk.py
apexomni/common/__init__.py
apexomni/common/libzklink_sdk.dylib
apexomni/common/libzklink_sdk.so
apexomni/common/zklink_sdk.dll
apexomni/common/zklink_sdk.py
apexomni/eth_signing/__init__.py
apexomni/eth_signing/eth_prive_action.py
apexomni/eth_signing/onboarding_action.py
apexomni/eth_signing/sign_off_chain_action.py
apexomni/eth_signing/signers.py
apexomni/eth_signing/util.py
apexomni/helpers/__init__.py
apexomni/helpers/db.py
apexomni/helpers/request_helpers.py
apexomni/helpers/requests.py
apexomni/helpers/util.py
apexomni/helpers/wordlists/__init__.py
apexomni/pc/__init__.py
apexomni/pc/zklink_sdk.dll
apexomni/pc/zklink_sdk.py
apexomni/pc/linux_arm/__init__.py
apexomni/pc/linux_arm/libzklink_sdk.so
apexomni/pc/linux_arm/zklink_sdk.py
apexomni/pc/linux_x86/__init__.py
apexomni/pc/linux_x86/libzklink_sdk.so
apexomni/pc/linux_x86/zklink_sdk.py
apexomni/starkex/__init__.py
apexomni/starkex/conditional_transfer.py
apexomni/starkex/constants.py
apexomni/starkex/helpers.py
apexomni/starkex/order.py
apexomni/starkex/signable.py
apexomni/starkex/transfer.py
apexomni/starkex/withdrawal.py
apexomni/starkex/starkex_resources/__init__.py
apexomni/starkex/starkex_resources/cpp_signature.py
apexomni/starkex/starkex_resources/math_utils.py
apexomni/starkex/starkex_resources/pedersen_params.json
apexomni/starkex/starkex_resources/proxy.py
apexomni/starkex/starkex_resources/python_signature.py
apexomni/x86/__init__.py
apexomni/x86/libzklink_sdk.dylib
apexomni/x86/zklink_sdk.py
apexomni-3.1.7.dist-info/licenses/LICENSE
tests/__init__.py
tests/account_value.py
apexomni-3.1.7.dist-info/METADATA
apexomni-3.1.7.dist-info/WHEEL
apexomni-3.1.7.dist-info/top_level.txt
apexomni-3.1.7.dist-info/RECORD
