Metadata-Version: 2.4
Name: apexomni
Version: 3.1.7
Summary: Python3 Apexpro omni HTTP/WebSocket API Connector
Home-page: https://github.com/ApeX-Protocol/apexpro-openapi
Author: Dexter Dickinson
Author-email: Dexter Dickinson <xxx@apexomni.com>
Classifier: Development Status :: 4 - Beta
Classifier: Intended Audience :: Developers
Classifier: Topic :: Software Development :: Libraries :: Python Modules
Classifier: License :: OSI Approved :: MIT License
Classifier: Programming Language :: Python :: 3.6
Classifier: Programming Language :: Python :: 3.7
Classifier: Programming Language :: Python :: 3.8
Classifier: Programming Language :: Python :: 3.9
Classifier: Programming Language :: Python :: 3.10
Classifier: Programming Language :: Python :: 3.11
Classifier: Programming Language :: Python :: 3.12
Requires-Python: >=3.6
License-File: LICENSE
Requires-Dist: requests
Requires-Dist: websocket-client
Requires-Dist: websockets
Requires-Dist: dateparser==1.0.0
Requires-Dist: ecdsa==0.16.0
Requires-Dist: eth_keys
Requires-Dist: eth-account==0.13.7
Requires-Dist: mpmath==1.0.0
Requires-Dist: pytest<5.0.0,>=4.4.0
Requires-Dist: requests-mock==1.6.0
Requires-Dist: requests<3.0.0,>=2.32.3
Requires-Dist: setuptools>=50.3.2
Requires-Dist: sympy==1.6
Requires-Dist: tox==3.13.2
Requires-Dist: web3==6.0.0
Dynamic: author
Dynamic: home-page
Dynamic: license-file
Dynamic: requires-python
